{
  "url": "http://0.0.0.0:8001/sync-plaintext-no-params",
  "connections": 10,
  "sampleInt": 1000,
  "pipelining": 1,
  "workers": 0,
  "duration": 11.01,
  "samples": 11,
  "start": "2022-08-03T04:40:59.992Z",
  "finish": "2022-08-03T04:41:10.999Z",
  "errors": 0,
  "timeouts": 0,
  "mismatches": 0,
  "non2xx": 0,
  "resets": 0,
  "1xx": 0,
  "2xx": 663881,
  "3xx": 0,
  "4xx": 0,
  "5xx": 0,
  "statusCodeStats": { "200": { "count": 663881 } },
  "latency": {
    "average": 0.01,
    "mean": 0.01,
    "stddev": 0.03,
    "min": 1,
    "max": 7,
    "p0_001": 0,
    "p0_01": 0,
    "p0_1": 0,
    "p1": 0,
    "p2_5": 0,
    "p10": 0,
    "p25": 0,
    "p50": 0,
    "p75": 0,
    "p90": 0,
    "p97_5": 0,
    "p99": 0,
    "p99_9": 0,
    "p99_99": 0,
    "p99_999": 5,
    "totalCount": 663881
  },
  "requests": {
    "average": 60354.91,
    "mean": 60354.91,
    "stddev": 2230.12,
    "min": 57975,
    "max": 66609,
    "total": 663881,
    "p0_001": 57983,
    "p0_01": 57983,
    "p0_1": 57983,
    "p1": 57983,
    "p2_5": 57983,
    "p10": 58527,
    "p25": 58687,
    "p50": 60415,
    "p75": 60831,
    "p90": 61183,
    "p97_5": 66623,
    "p99": 66623,
    "p99_9": 66623,
    "p99_99": 66623,
    "p99_999": 66623,
    "sent": 663891
  },
  "throughput": {
    "average": 8873053.1,
    "mean": 8873053.1,
    "stddev": 328633.22,
    "min": 8522325,
    "max": 9791523,
    "total": 97590507,
    "p0_001": 8527871,
    "p0_01": 8527871,
    "p0_1": 8527871,
    "p1": 8527871,
    "p2_5": 8527871,
    "p10": 8609791,
    "p25": 8626175,
    "p50": 8880127,
    "p75": 8945663,
    "p90": 8994815,
    "p97_5": 9797631,
    "p99": 9797631,
    "p99_9": 9797631,
    "p99_99": 9797631,
    "p99_999": 9797631
  }
}
