{
  "url": "http://0.0.0.0:8001/async-plaintext-query-param?first=abc",
  "connections": 25,
  "pipelining": 1,
  "workers": 4,
  "duration": 5,
  "start": "2022-01-30T23:17:10.022Z",
  "finish": "2022-01-30T23:17:15.026Z",
  "errors": 0,
  "timeouts": 0,
  "mismatches": 0,
  "non2xx": 0,
  "resets": 0,
  "1xx": 0,
  "2xx": 285091,
  "3xx": 0,
  "4xx": 0,
  "5xx": 0,
  "statusCodeStats": { "200": { "count": 285091 } },
  "latency": {
    "average": 0.05,
    "mean": 0.05,
    "stddev": 1.19,
    "min": 1,
    "max": 152,
    "p0_001": 0,
    "p0_01": 0,
    "p0_1": 0,
    "p1": 0,
    "p2_5": 0,
    "p10": 0,
    "p25": 0,
    "p50": 0,
    "p75": 0,
    "p90": 0,
    "p97_5": 0,
    "p99": 1,
    "p99_9": 7,
    "p99_99": 56,
    "p99_999": 126,
    "totalCount": 285091
  },
  "requests": {
    "average": 57014.4,
    "mean": 57014.4,
    "stddev": 1419.8,
    "min": 55568,
    "max": 59742,
    "total": 285091,
    "p0_001": 55583,
    "p0_01": 55583,
    "p0_1": 55583,
    "p1": 55583,
    "p2_5": 55583,
    "p10": 55583,
    "p25": 56383,
    "p50": 56639,
    "p75": 56799,
    "p90": 59743,
    "p97_5": 59743,
    "p99": 59743,
    "p99_9": 59743,
    "p99_99": 59743,
    "p99_999": 59743,
    "sent": 285115
  },
  "throughput": {
    "average": 7754137.6,
    "mean": 7754137.6,
    "stddev": 193400.62,
    "min": 7557248,
    "max": 8124912,
    "total": 38772376,
    "p0_001": 7561215,
    "p0_01": 7561215,
    "p0_1": 7561215,
    "p1": 7561215,
    "p2_5": 7561215,
    "p10": 7561215,
    "p25": 7667711,
    "p50": 7700479,
    "p75": 7725055,
    "p90": 8126463,
    "p97_5": 8126463,
    "p99": 8126463,
    "p99_9": 8126463,
    "p99_99": 8126463,
    "p99_999": 8126463
  }
}
